cloudshell/__init__.py
cloudshell/template/__init__.py
cloudshell/template/a.py
cloudshell/template/package.py
tests/__init__.py
tests/cloudshell/__init__.py
tests/cloudshell/test_package.py
cloudshell_template-1.4.2.dist-info/METADATA
cloudshell_template-1.4.2.dist-info/WHEEL
cloudshell_template-1.4.2.dist-info/top_level.txt
cloudshell_template-1.4.2.dist-info/RECORD
