Metadata-Version: 2.1
Name: cloudshell-template
Version: 1.4.2
Summary: <your package description>
Home-page: http://www.qualisystems.com/
Author: QualiSystems
Author-email: info@qualisystems.com
Requires-Python: ~=3.7
Requires-Dist: cloudshell-shell-core (~=5.1)
